zelos/__init__.py
zelos/__main__.py
zelos/breakpoints.py
zelos/config_gen.py
zelos/engine.py
zelos/enums.py
zelos/exceptions.py
zelos/feeds.py
zelos/file_system.py
zelos/hooks.py
zelos/manager.py
zelos/memory.py
zelos/modules.py
zelos/processes.py
zelos/scheduler.py
zelos/state.py
zelos/symbol_manager.py
zelos/threads.py
zelos/triggers.py
zelos/util.py
zelos/zml.py
zelos/api/__init__.py
zelos/api/memory_api.py
zelos/api/regs_api.py
zelos/api/zelos_api.py
zelos/emulator/__init__.py
zelos/emulator/arm.py
zelos/emulator/base.py
zelos/emulator/mips.py
zelos/emulator/x86.py
zelos/emulator/x86_gdt.py
zelos/ext/env/linux-armv7/etc/hosts
zelos/ext/env/linux-armv7/etc/resolv.conf
zelos/ext/env/linux-armv7/lib/ld-linux-armhf.so.3
zelos/ext/env/linux-armv7/lib/ld-linux.so.3
zelos/ext/env/linux-armv7/lib/ld-uClibc-0.9.33.2.so
zelos/ext/env/linux-armv7/lib/ld-uClibc-1.0.31.so
zelos/ext/env/linux-armv7/lib/ld-uClibc.so
zelos/ext/env/linux-armv7/lib/ld-uClibc.so.0
zelos/ext/env/linux-armv7/lib/ld-uClibc.so.1
zelos/ext/env/linux-armv7/lib/libc++.so
zelos/ext/env/linux-armv7/lib/libc.so
zelos/ext/env/linux-armv7/lib/libc.so.0
zelos/ext/env/linux-armv7/lib/libc.so.1
zelos/ext/env/linux-armv7/lib/libc.so.6
zelos/ext/env/linux-armv7/lib/libcrypt.so.0
zelos/ext/env/linux-armv7/lib/libdl.so
zelos/ext/env/linux-armv7/lib/libgcc_s.so.1
zelos/ext/env/linux-armv7/lib/liblog.so
zelos/ext/env/linux-armv7/lib/libm.so
zelos/ext/env/linux-armv7/lib/libm.so.0
zelos/ext/env/linux-armv7/lib/libstdc++.so
zelos/ext/env/linux-armv7/lib/libuClibc-1.0.31.so
zelos/ext/env/linux-armv7/lib/libz.so
zelos/ext/env/linux-armv7/proc/net/route
zelos/ext/env/linux-armv7/usr/lib/README.md
zelos/ext/env/linux-armv7/usr/lib/libconfig.so
zelos/ext/env/linux-mips/etc/hosts
zelos/ext/env/linux-mips/etc/resolv.conf
zelos/ext/env/linux-x86/etc/hosts
zelos/ext/env/linux-x86/etc/ld.so.cache
zelos/ext/env/linux-x86/etc/resolv.conf
zelos/ext/env/linux-x86/lib/ld-linux.so.2
zelos-0.2.0.dist-info/AUTHORS.md
zelos-0.2.0.dist-info/LICENSE
zelos-0.2.0.dist-info/METADATA
zelos-0.2.0.dist-info/WHEEL
zelos-0.2.0.dist-info/entry_points.txt
zelos-0.2.0.dist-info/top_level.txt
zelos-0.2.0.dist-info/RECORD
