Metadata-Version: 2.1
Name: zelos
Version: 0.2.0
Summary: A comprehensive binary emulation platform.
Home-page: https://github.com/zeropointdynamics/zelos
Author: Zeropoint Dynamics
Author-email: zelos@zeropointdynamics.com
Maintainer: Zeropoint Dynamics
Maintainer-email: zelos@zeropointdynamics.com
License: AGPLv3
Project-URL: Documentation, https://zelos.zeropointdynamics.com/
Project-URL: Bug Tracker, https://github.com/zeropointdynamics/zelos/issues
Project-URL: Source Code, https://github.com/zeropointdynamics/zelos
Keywords: emulation,dynamic analysis,binary analysis
Platform: UNKNOWN
Classifier: Development Status :: 4 - Beta
Classifier: Natural Language :: English
Classifier: License :: OSI Approved :: GNU Affero General Public License v3
Classifier: Operating System :: OS Independent
Classifier: Programming Language :: Python
Classifier: Programming Language :: Python :: 3
Classifier: Programming Language :: Python :: 3.6
Classifier: Programming Language :: Python :: 3.7
Classifier: Programming Language :: Python :: 3.8
Requires-Python: >=3.6.0
Requires-Dist: wheel
Requires-Dist: colorama (==0.4.1)
Requires-Dist: termcolor (==1.1.0)
Requires-Dist: capstone (==4.0.1)
Requires-Dist: sortedcontainers (==2.1.0)
Requires-Dist: verboselogs (==1.7)
Requires-Dist: dnslib (==0.9.10)
Requires-Dist: hexdump (==3.3)
Requires-Dist: dpkt (==1.9.2)
Requires-Dist: coloredlogs (==10.0)
Requires-Dist: configargparse (==0.15.1)
Requires-Dist: pypacker (==4.9)
Requires-Dist: lief (>=0.9.0)
Requires-Dist: zebracorn (==0.0.1)
Requires-Dist: lark-parser (==0.7.8)
Provides-Extra: azure-pipelines
Requires-Dist: coverage ; extra == 'azure-pipelines'
Requires-Dist: hypothesis ; extra == 'azure-pipelines'
Requires-Dist: pympler ; extra == 'azure-pipelines'
Requires-Dist: pytest-cov ; extra == 'azure-pipelines'
Requires-Dist: pytest (>=4.3.0) ; extra == 'azure-pipelines'
Requires-Dist: pytest-xdist ; extra == 'azure-pipelines'
Requires-Dist: filelock ; extra == 'azure-pipelines'
Requires-Dist: yara-python ; extra == 'azure-pipelines'
Requires-Dist: mock ; extra == 'azure-pipelines'
Requires-Dist: pytest-azurepipelines ; extra == 'azure-pipelines'
Provides-Extra: dev
Requires-Dist: coverage ; extra == 'dev'
Requires-Dist: hypothesis ; extra == 'dev'
Requires-Dist: pympler ; extra == 'dev'
Requires-Dist: pytest-cov ; extra == 'dev'
Requires-Dist: pytest (>=4.3.0) ; extra == 'dev'
Requires-Dist: pytest-xdist ; extra == 'dev'
Requires-Dist: filelock ; extra == 'dev'
Requires-Dist: yara-python ; extra == 'dev'
Requires-Dist: mock ; extra == 'dev'
Requires-Dist: sphinx (==2.4.4) ; extra == 'dev'
Requires-Dist: sphinx-rtd-theme ; extra == 'dev'
Requires-Dist: sphinxcontrib-apidoc ; extra == 'dev'
Requires-Dist: recommonmark ; extra == 'dev'
Requires-Dist: sphinx-argparse ; extra == 'dev'
Requires-Dist: pre-commit ; extra == 'dev'
Requires-Dist: tox ; extra == 'dev'
Provides-Extra: docs
Requires-Dist: sphinx (==2.4.4) ; extra == 'docs'
Requires-Dist: sphinx-rtd-theme ; extra == 'docs'
Requires-Dist: sphinxcontrib-apidoc ; extra == 'docs'
Requires-Dist: recommonmark ; extra == 'docs'
Requires-Dist: sphinx-argparse ; extra == 'docs'
Provides-Extra: tests
Requires-Dist: coverage ; extra == 'tests'
Requires-Dist: hypothesis ; extra == 'tests'
Requires-Dist: pympler ; extra == 'tests'
Requires-Dist: pytest-cov ; extra == 'tests'
Requires-Dist: pytest (>=4.3.0) ; extra == 'tests'
Requires-Dist: pytest-xdist ; extra == 'tests'
Requires-Dist: filelock ; extra == 'tests'
Requires-Dist: yara-python ; extra == 'tests'
Requires-Dist: mock ; extra == 'tests'
